seismon
