Metadata-Version: 2.1
Name: seismon
Version: 0.0.6
Summary: A python package for mitigating the effects of earthquakes on GW detectors
Home-page: https://github.com/gwdetchar/seismon/
Author: Michael Coughlin
Author-email: michael.coughlin@ligo.org
License: GPL-2.0-or-later
Platform: UNKNOWN
Classifier: Development Status :: 4 - Beta
Classifier: Programming Language :: Python
Classifier: Programming Language :: Python :: 3.7
Classifier: Programming Language :: Python :: 3.8
Classifier: Programming Language :: Python :: 3.9
Classifier: Programming Language :: Python :: 3.10
Classifier: Intended Audience :: Science/Research
Classifier: Intended Audience :: End Users/Desktop
Classifier: Intended Audience :: Developers
Classifier: Natural Language :: English
Classifier: Topic :: Scientific/Engineering
Classifier: Topic :: Scientific/Engineering :: Astronomy
Classifier: Topic :: Scientific/Engineering :: Physics
Classifier: Operating System :: POSIX
Classifier: Operating System :: Unix
Classifier: Operating System :: MacOS
Classifier: License :: OSI Approved :: GNU General Public License v3 (GPLv3)
Provides: seismon
Provides-Extra: frontend
License-File: LICENSE
